wbmaker/__init__.py
wbmaker/item.py
wbmaker/wb.py
wbmaker-0.0.12.dist-info/LICENSE
wbmaker-0.0.12.dist-info/METADATA
wbmaker-0.0.12.dist-info/WHEEL
wbmaker-0.0.12.dist-info/RECORD
