Metadata-Version: 2.1
Name: wbmaker
Version: 0.0.12
Summary: Establishes a connection to a Wikibase instance and provides methods for interacting with it.
Home-page: https://github.com/skybristol/wbmaker
License: MIT
Keywords: wikibase,wikibaseintegrator,mwclient
Author: Sky Bristol
Author-email: skybristol@gmail.com
Requires-Python: >=3.11,<4.0
Classifier: Development Status :: 3 - Alpha
Classifier: Intended Audience :: Developers
Classifier: License :: OSI Approved :: MIT License
Classifier: Programming Language :: Python :: 3
Classifier: Programming Language :: Python :: 3.11
Classifier: Programming Language :: Python :: 3.12
Classifier: Topic :: Software Development :: Libraries
Requires-Dist: mwclient (>=0.10.1,<0.11.0)
Requires-Dist: networkx (>=3.0,<4.0)
Requires-Dist: pandas (>=2.0.0,<3.0.0)
Requires-Dist: python-dotenv (>=1.0.0,<2.0.0)
Requires-Dist: requests (>=2.28.2,<3.0.0)
Requires-Dist: wikibaseintegrator (>=0.12.4,<0.13.0)
